[
  {
    "id": "1d7738e2-e4d9-41d5-9327-6657ae7e9bbc",
    "user_id": "370621bf-3d54-4c3f-ae21-97a30062b0f9",
    "task": "atlantis timesheet issue",
    "is_completed": false,
    "due_date": "2025-07-16",
    "priority": "Medium",
    "created_at": "2025-07-16T16:51:56.779152+00:00",
    "updated_at": "2025-07-22T05:01:24.539251+00:00",
    "completed": true,
    "pinned": false,
    "display_order": 6,
    "sort_order": null
  },
  {
    "id": "36bcc1d3-86ae-4294-859d-2b6d409e5e1a",
    "user_id": "370621bf-3d54-4c3f-ae21-97a30062b0f9",
    "task": "transfer funds to india",
    "is_completed": false,
    "due_date": "2025-07-16",
    "priority": "Medium",
    "created_at": "2025-07-16T07:42:12.886443+00:00",
    "updated_at": "2025-08-02T22:46:22.572116+00:00",
    "completed": true,
    "pinned": false,
    "display_order": 10,
    "sort_order": 16
  },
  {
    "id": "5c107125-d6b9-4d86-aff8-7357defe5a00",
    "user_id": "370621bf-3d54-4c3f-ae21-97a30062b0f9",
    "task": "debt consulation",
    "is_completed": false,
    "due_date": "2025-07-16",
    "priority": "Medium",
    "created_at": "2025-07-16T07:41:25.137993+00:00",
    "updated_at": "2025-08-02T22:46:23.846915+00:00",
    "completed": true,
    "pinned": false,
    "display_order": 15,
    "sort_order": 3
  },
  {
    "id": "fc06fba6-3ad9-44d5-bad7-327b85e5b17f",
    "user_id": "370621bf-3d54-4c3f-ae21-97a30062b0f9",
    "task": "substitute teacher application.",
    "is_completed": false,
    "due_date": "2025-07-13",
    "priority": "Medium",
    "created_at": "2025-07-13T22:59:22.576309+00:00",
    "updated_at": "2025-08-03T00:04:32.098872+00:00",
    "completed": true,
    "pinned": false,
    "display_order": 23,
    "sort_order": 20
  },
  {
    "id": "7982bb0f-13e4-4269-89bf-cdcbc12996fb",
    "user_id": "55a76048-3516-41e0-a72a-04f29ef3f518",
    "task": "dfgfdgfdg",
    "is_completed": false,
    "due_date": "2025-07-17",
    "priority": "Medium",
    "created_at": "2025-07-17T12:18:26.275267+00:00",
    "updated_at": "2025-07-22T05:01:24.628453+00:00",
    "completed": true,
    "pinned": false,
    "display_order": 0,
    "sort_order": 19
  },
  {
    "id": "732cad1b-abcd-46dd-b55c-1e513d4983ac",
    "user_id": "370621bf-3d54-4c3f-ae21-97a30062b0f9",
    "task": "complete the w9 form and send the bank details",
    "is_completed": false,
    "due_date": "2025-07-16",
    "priority": "Medium",
    "created_at": "2025-07-16T05:50:30.34311+00:00",
    "updated_at": "2025-07-22T05:01:24.697065+00:00",
    "completed": true,
    "pinned": false,
    "display_order": 17,
    "sort_order": null
  },
  {
    "id": "0db9ba8d-8b3d-445e-a9c9-53c06eda5582",
    "user_id": "55a76048-3516-41e0-a72a-04f29ef3f518",
    "task": "6fdgdg",
    "is_completed": false,
    "due_date": "2025-07-17",
    "priority": "Medium",
    "created_at": "2025-07-17T12:18:20.459935+00:00",
    "updated_at": "2025-07-22T05:01:22.449591+00:00",
    "completed": true,
    "pinned": false,
    "display_order": 0,
    "sort_order": 8
  },
  {
    "id": "1aa16a9a-e55a-47a4-b972-7f5e62410a83",
    "user_id": "55a76048-3516-41e0-a72a-04f29ef3f518",
    "task": "fdgdfgfdg",
    "is_completed": false,
    "due_date": "2025-07-17",
    "priority": "Medium",
    "created_at": "2025-07-17T12:18:21.530426+00:00",
    "updated_at": "2025-07-22T05:01:22.765035+00:00",
    "completed": true,
    "pinned": false,
    "display_order": 0,
    "sort_order": 10
  },
  {
    "id": "74a56e9a-fe51-45f2-9985-d0a4ff781316",
    "user_id": "370621bf-3d54-4c3f-ae21-97a30062b0f9",
    "task": "Paint garage door",
    "is_completed": false,
    "due_date": "2025-07-22",
    "priority": "Medium",
    "created_at": "2025-07-14T04:37:03.289979+00:00",
    "updated_at": "2025-07-22T05:01:22.915971+00:00",
    "completed": true,
    "pinned": false,
    "display_order": 20,
    "sort_order": 11
  },
  {
    "id": "d14b58e9-d81f-4129-8747-06ffcfa88c83",
    "user_id": "370621bf-3d54-4c3f-ae21-97a30062b0f9",
    "task": "pay india lic",
    "is_completed": false,
    "due_date": "2025-07-21",
    "priority": "Medium",
    "created_at": "2025-07-16T07:42:35.636233+00:00",
    "updated_at": "2025-08-04T17:33:13.076375+00:00",
    "completed": true,
    "pinned": true,
    "display_order": 8,
    "sort_order": 6
  },
  {
    "id": "bed52e42-fcc9-4334-882b-d72e3e3174a5",
    "user_id": "370621bf-3d54-4c3f-ae21-97a30062b0f9",
    "task": "complete school returning forms",
    "is_completed": false,
    "due_date": "2025-07-16",
    "priority": "Medium",
    "created_at": "2025-07-16T03:42:23.510711+00:00",
    "updated_at": "2025-07-22T05:01:24.843594+00:00",
    "completed": true,
    "pinned": false,
    "display_order": 18,
    "sort_order": null
  },
  {
    "id": "11815e0d-78d7-4a00-8687-a78641e352f1",
    "user_id": "370621bf-3d54-4c3f-ae21-97a30062b0f9",
    "task": "tmobile bill",
    "is_completed": false,
    "due_date": "2025-07-14",
    "priority": "Medium",
    "created_at": "2025-07-14T05:17:14.870433+00:00",
    "updated_at": "2025-07-22T05:01:24.919002+00:00",
    "completed": true,
    "pinned": false,
    "display_order": 19,
    "sort_order": null
  },
  {
    "id": "5d6aa180-8324-4682-af63-03f2d577660e",
    "user_id": "55a76048-3516-41e0-a72a-04f29ef3f518",
    "task": "create a task",
    "is_completed": false,
    "due_date": "2025-07-17",
    "priority": "Medium",
    "created_at": "2025-07-17T11:00:21.457175+00:00",
    "updated_at": "2025-07-22T05:01:24.99032+00:00",
    "completed": true,
    "pinned": true,
    "display_order": 2,
    "sort_order": 1
  },
  {
    "id": "24397ebf-22fc-454c-b65a-081ae8ccba98",
    "user_id": "370621bf-3d54-4c3f-ae21-97a30062b0f9",
    "task": "Clean the garage",
    "is_completed": false,
    "due_date": "2025-07-14",
    "priority": "Medium",
    "created_at": "2025-07-14T02:21:07.243872+00:00",
    "updated_at": "2025-08-06T00:48:28.025118+00:00",
    "completed": true,
    "pinned": false,
    "display_order": 21,
    "sort_order": 9
  },
  {
    "id": "da784207-d1c5-4f54-adc9-6b5fefa7d482",
    "user_id": "370621bf-3d54-4c3f-ae21-97a30062b0f9",
    "task": "sams returns",
    "is_completed": false,
    "due_date": "2025-07-25",
    "priority": "Medium",
    "created_at": "2025-07-25T03:29:24.959932+00:00",
    "updated_at": "2025-08-04T17:42:09.13689+00:00",
    "completed": true,
    "pinned": false,
    "display_order": 0,
    "sort_order": 9
  },
  {
    "id": "f4cf8554-0565-42f3-9c94-52bb2fa1955f",
    "user_id": "55a76048-3516-41e0-a72a-04f29ef3f518",
    "task": "fgdfgfdgfdg",
    "is_completed": false,
    "due_date": "2025-07-17",
    "priority": "Medium",
    "created_at": "2025-07-17T12:18:25.040294+00:00",
    "updated_at": "2025-07-22T05:01:25.214351+00:00",
    "completed": true,
    "pinned": false,
    "display_order": 0,
    "sort_order": 13
  },
  {
    "id": "744336f1-b957-42ca-93f6-fe602888ffaf",
    "user_id": "55a76048-3516-41e0-a72a-04f29ef3f518",
    "task": "dfgdfgfdg",
    "is_completed": false,
    "due_date": "2025-07-17",
    "priority": "Medium",
    "created_at": "2025-07-17T12:18:22.364343+00:00",
    "updated_at": "2025-07-22T05:01:23.47526+00:00",
    "completed": true,
    "pinned": false,
    "display_order": 0,
    "sort_order": 9
  },
  {
    "id": "38936893-644c-4d7f-8216-d00ea9f1c1db",
    "user_id": "370621bf-3d54-4c3f-ae21-97a30062b0f9",
    "task": "usps return tomorrow",
    "is_completed": false,
    "due_date": "2025-07-13",
    "priority": "Medium",
    "created_at": "2025-07-13T22:58:20.932563+00:00",
    "updated_at": "2025-07-22T05:01:25.279414+00:00",
    "completed": true,
    "pinned": false,
    "display_order": 28,
    "sort_order": null
  },
  {
    "id": "61a02fea-224b-444f-a0a6-c37b57411baa",
    "user_id": "370621bf-3d54-4c3f-ae21-97a30062b0f9",
    "task": "amazon returns",
    "is_completed": false,
    "due_date": "2025-07-26",
    "priority": "Medium",
    "created_at": "2025-07-20T20:16:02.198994+00:00",
    "updated_at": "2025-08-04T17:42:21.897714+00:00",
    "completed": true,
    "pinned": false,
    "display_order": 0,
    "sort_order": 11
  },
  {
    "id": "d0b3c22e-970e-42c0-9da0-1c497708c51f",
    "user_id": "55a76048-3516-41e0-a72a-04f29ef3f518",
    "task": "tetets666",
    "is_completed": false,
    "due_date": "2025-07-17",
    "priority": "Medium",
    "created_at": "2025-07-17T12:18:18.213541+00:00",
    "updated_at": "2025-07-22T05:01:23.78894+00:00",
    "completed": true,
    "pinned": true,
    "display_order": 0,
    "sort_order": 6
  },
  {
    "id": "2ea5faba-63b1-454b-9d0e-8c7f0fdd8884",
    "user_id": "55a76048-3516-41e0-a72a-04f29ef3f518",
    "task": "dfgdfgfdg",
    "is_completed": false,
    "due_date": "2025-07-17",
    "priority": "Medium",
    "created_at": "2025-07-17T12:18:24.003381+00:00",
    "updated_at": "2025-07-22T05:01:25.575021+00:00",
    "completed": true,
    "pinned": false,
    "display_order": 0,
    "sort_order": 12
  },
  {
    "id": "e0625ed5-98da-4368-8374-1841138fb68a",
    "user_id": "370621bf-3d54-4c3f-ae21-97a30062b0f9",
    "task": "kohls return",
    "is_completed": false,
    "due_date": "2025-07-31",
    "priority": "Medium",
    "created_at": "2025-07-31T16:44:45.260192+00:00",
    "updated_at": "2025-08-04T17:42:28.510198+00:00",
    "completed": true,
    "pinned": false,
    "display_order": 0,
    "sort_order": 1
  },
  {
    "id": "100cbf6f-0793-40c7-9120-57ae38f2d87d",
    "user_id": "370621bf-3d54-4c3f-ae21-97a30062b0f9",
    "task": "school supplies",
    "is_completed": false,
    "due_date": "2025-07-13",
    "priority": "Medium",
    "created_at": "2025-07-13T22:58:49.773316+00:00",
    "updated_at": "2025-07-31T15:18:22.320031+00:00",
    "completed": true,
    "pinned": false,
    "display_order": 26,
    "sort_order": 21
  },
  {
    "id": "d5b2d2cf-d463-45b0-8c4e-601884caf766",
    "user_id": "370621bf-3d54-4c3f-ae21-97a30062b0f9",
    "task": "upload h1b documents",
    "is_completed": false,
    "due_date": "2025-07-31",
    "priority": "Medium",
    "created_at": "2025-07-31T15:16:37.884338+00:00",
    "updated_at": "2025-08-06T06:00:02.924027+00:00",
    "completed": true,
    "pinned": true,
    "display_order": 0,
    "sort_order": 1
  },
  {
    "id": "46dc604e-4047-4728-9885-e4d087273aa7",
    "user_id": "370621bf-3d54-4c3f-ae21-97a30062b0f9",
    "task": "july report",
    "is_completed": false,
    "due_date": "2025-07-31",
    "priority": "Medium",
    "created_at": "2025-07-30T21:50:52.229335+00:00",
    "updated_at": "2025-08-06T06:00:14.901603+00:00",
    "completed": true,
    "pinned": false,
    "display_order": 0,
    "sort_order": 6
  },
  {
    "id": "e815731e-9014-40df-90be-82f4c53c167b",
    "user_id": "55a76048-3516-41e0-a72a-04f29ef3f518",
    "task": "task default",
    "is_completed": false,
    "due_date": "2025-07-22",
    "priority": "Medium",
    "created_at": "2025-07-22T05:34:21.907541+00:00",
    "updated_at": "2025-08-01T06:50:28.298752+00:00",
    "completed": false,
    "pinned": true,
    "display_order": 0,
    "sort_order": 20
  },
  {
    "id": "6947fe04-c95d-4d39-b183-7e6b532fd248",
    "user_id": "55a76048-3516-41e0-a72a-04f29ef3f518",
    "task": "task today",
    "is_completed": false,
    "due_date": "2025-07-22",
    "priority": "Medium",
    "created_at": "2025-07-22T05:35:38.412807+00:00",
    "updated_at": "2025-08-01T06:50:30.737694+00:00",
    "completed": false,
    "pinned": true,
    "display_order": 0,
    "sort_order": 21
  },
  {
    "id": "77619bc9-161d-44ff-89f4-3f10095791cb",
    "user_id": "370621bf-3d54-4c3f-ae21-97a30062b0f9",
    "task": "close the pnc account",
    "is_completed": false,
    "due_date": "2025-08-29",
    "priority": "Medium",
    "created_at": "2025-07-20T13:29:53.197499+00:00",
    "updated_at": "2025-08-12T14:42:58.320669+00:00",
    "completed": false,
    "pinned": false,
    "display_order": 0,
    "sort_order": 8
  },
  {
    "id": "f10851b7-c2cf-4219-bcab-94bba5dac4b9",
    "user_id": "370621bf-3d54-4c3f-ae21-97a30062b0f9",
    "task": "setup auto insurance payment on emi",
    "is_completed": false,
    "due_date": "2025-08-04",
    "priority": "Medium",
    "created_at": "2025-08-04T17:43:19.682793+00:00",
    "updated_at": "2025-08-06T06:00:29.771598+00:00",
    "completed": true,
    "pinned": false,
    "display_order": 0,
    "sort_order": 3
  },
  {
    "id": "9a99ca17-0302-4c3d-ad86-ac650b6a0220",
    "user_id": "370621bf-3d54-4c3f-ae21-97a30062b0f9",
    "task": "buy shoes for yourself",
    "is_completed": false,
    "due_date": "2025-08-09",
    "priority": "Medium",
    "created_at": "2025-08-09T01:13:24.008587+00:00",
    "updated_at": "2025-08-13T13:01:32.256627+00:00",
    "completed": true,
    "pinned": false,
    "display_order": 0,
    "sort_order": 1
  },
  {
    "id": "0cec7cd6-6332-4d60-97df-4a8ef23ff94e",
    "user_id": "03011a8d-a034-4d28-a98e-10710b44c4ad",
    "task": "pay india tution fee",
    "is_completed": false,
    "due_date": "2025-07-16",
    "priority": "Medium",
    "created_at": "2025-07-16T07:42:26.201609+00:00",
    "updated_at": "2025-07-22T05:01:25.947492+00:00",
    "completed": false,
    "pinned": false,
    "display_order": 9,
    "sort_order": 7
  },
  {
    "id": "b1139057-7b57-4c21-adad-2149e1035d43",
    "user_id": "55a76048-3516-41e0-a72a-04f29ef3f518",
    "task": "task tomorrow",
    "is_completed": false,
    "due_date": "2025-07-23",
    "priority": "Medium",
    "created_at": "2025-07-22T05:35:50.249373+00:00",
    "updated_at": "2025-07-22T05:35:50.249373+00:00",
    "completed": false,
    "pinned": false,
    "display_order": 0,
    "sort_order": 22
  },
  {
    "id": "8635f30c-54d3-4a9f-9d3d-629b620238ca",
    "user_id": "370621bf-3d54-4c3f-ae21-97a30062b0f9",
    "task": "urologist",
    "is_completed": false,
    "due_date": "2025-08-15",
    "priority": "Medium",
    "created_at": "2025-07-16T07:41:51.825859+00:00",
    "updated_at": "2025-08-12T14:42:58.238086+00:00",
    "completed": false,
    "pinned": false,
    "display_order": 12,
    "sort_order": 7
  },
  {
    "id": "b914ba38-d5ab-4168-af42-74185fb8c995",
    "user_id": "370621bf-3d54-4c3f-ae21-97a30062b0f9",
    "task": "atom enrollment in november",
    "is_completed": false,
    "due_date": "2025-11-01",
    "priority": "Medium",
    "created_at": "2025-07-16T07:42:04.994181+00:00",
    "updated_at": "2025-08-12T14:42:58.417575+00:00",
    "completed": false,
    "pinned": false,
    "display_order": 11,
    "sort_order": 9
  },
  {
    "id": "5705a648-9290-49f4-af65-93f5d696467d",
    "user_id": "370621bf-3d54-4c3f-ae21-97a30062b0f9",
    "task": "pay sbi life",
    "is_completed": false,
    "due_date": "2025-07-22",
    "priority": "Medium",
    "created_at": "2025-07-16T07:42:41.589751+00:00",
    "updated_at": "2025-08-06T06:06:01.136266+00:00",
    "completed": true,
    "pinned": false,
    "display_order": 7,
    "sort_order": 12
  },
  {
    "id": "6a72b21a-b943-4ca9-9293-3e665aa1a80a",
    "user_id": "370621bf-3d54-4c3f-ae21-97a30062b0f9",
    "task": "send remaining H1B documents",
    "is_completed": false,
    "due_date": "2025-08-08",
    "priority": "Medium",
    "created_at": "2025-08-09T01:12:50.590008+00:00",
    "updated_at": "2025-08-12T14:42:17.436129+00:00",
    "completed": false,
    "pinned": true,
    "display_order": 0,
    "sort_order": 1
  },
  {
    "id": "3445cb7e-f46d-4977-b4e9-d1d5f5bd741b",
    "user_id": "370621bf-3d54-4c3f-ae21-97a30062b0f9",
    "task": "Send H4 documents",
    "is_completed": false,
    "due_date": "2025-08-12",
    "priority": "Medium",
    "created_at": "2025-08-12T14:42:31.198434+00:00",
    "updated_at": "2025-08-12T14:42:36.070508+00:00",
    "completed": false,
    "pinned": true,
    "display_order": 0,
    "sort_order": 1
  },
  {
    "id": "0d311a99-12be-4e59-b42a-b695c365e080",
    "user_id": "370621bf-3d54-4c3f-ae21-97a30062b0f9",
    "task": "sports physicals for sai ram",
    "is_completed": false,
    "due_date": "2025-07-13",
    "priority": "Medium",
    "created_at": "2025-07-13T22:59:02.208955+00:00",
    "updated_at": "2025-07-22T20:50:58.119553+00:00",
    "completed": true,
    "pinned": false,
    "display_order": 25,
    "sort_order": 17
  },
  {
    "id": "818a05dd-516b-4980-ba96-aeb3636a56ed",
    "user_id": "370621bf-3d54-4c3f-ae21-97a30062b0f9",
    "task": "sams return",
    "is_completed": false,
    "due_date": "2025-07-14",
    "priority": "Medium",
    "created_at": "2025-07-14T02:15:03.862093+00:00",
    "updated_at": "2025-07-25T03:29:54.639909+00:00",
    "completed": true,
    "pinned": false,
    "display_order": 22,
    "sort_order": 14
  },
  {
    "id": "2012a0fc-2baf-4a67-9de9-b56229828e40",
    "user_id": "370621bf-3d54-4c3f-ae21-97a30062b0f9",
    "task": "mental health",
    "is_completed": false,
    "due_date": "2025-07-16",
    "priority": "Medium",
    "created_at": "2025-07-16T07:41:16.870001+00:00",
    "updated_at": "2025-08-01T07:04:07.160775+00:00",
    "completed": true,
    "pinned": false,
    "display_order": 16,
    "sort_order": 19
  },
  {
    "id": "35f27960-b5d5-4aae-a639-8b28409dbd66",
    "user_id": "55a76048-3516-41e0-a72a-04f29ef3f518",
    "task": "a notification message: Generate a motivational morning notification for FinTask app. User has 0 pending tasks. Keep it under 50 characters, include emoji, be encouraging. Return only the message text, no quotes or extra formatting.",
    "is_completed": false,
    "due_date": "2025-08-16",
    "priority": "Medium",
    "created_at": "2025-08-16T08:07:44.831872+00:00",
    "updated_at": "2025-08-16T08:07:44.831872+00:00",
    "completed": false,
    "pinned": false,
    "display_order": 0,
    "sort_order": 1
  },
  {
    "id": "2becc71e-e9f3-4f77-8441-06c50f504db5",
    "user_id": "370621bf-3d54-4c3f-ae21-97a30062b0f9",
    "task": "recover pie wallet",
    "is_completed": false,
    "due_date": "2025-07-22",
    "priority": "Medium",
    "created_at": "2025-07-22T04:56:36.652322+00:00",
    "updated_at": "2025-08-01T19:15:37.673424+00:00",
    "completed": true,
    "pinned": false,
    "display_order": 0,
    "sort_order": 10
  },
  {
    "id": "47bd8b07-8a8f-4c80-abd0-d1e32f558e92",
    "user_id": "370621bf-3d54-4c3f-ae21-97a30062b0f9",
    "task": "go to costco",
    "is_completed": false,
    "due_date": "2025-07-28",
    "priority": "Medium",
    "created_at": "2025-07-28T23:40:05.912245+00:00",
    "updated_at": "2025-08-02T20:39:14.444483+00:00",
    "completed": true,
    "pinned": false,
    "display_order": 0,
    "sort_order": 5
  },
  {
    "id": "f2edb838-a693-4bb2-a9a2-3c80422df59b",
    "user_id": "55a76048-3516-41e0-a72a-04f29ef3f518",
    "task": "a notification message: Generate a motivational morning notification for FinTask app. User has 0 pending tasks. Keep it under 50 characters, include emoji, be encouraging. Return only the message text, no quotes or extra formatting.",
    "is_completed": false,
    "due_date": "2025-08-16",
    "priority": "Medium",
    "created_at": "2025-08-16T08:08:08.225434+00:00",
    "updated_at": "2025-08-16T08:08:08.225434+00:00",
    "completed": false,
    "pinned": false,
    "display_order": 0,
    "sort_order": 1
  },
  {
    "id": "b3572abb-c21d-4a29-a8cd-d890c5ec2f1d",
    "user_id": "55a76048-3516-41e0-a72a-04f29ef3f518",
    "task": "a notification message: Generate a motivational morning notification for FinTask app. User has 0 pending tasks. Keep it under 50 characters, include emoji, be encouraging. Return only the message text, no quotes or extra formatting.",
    "is_completed": false,
    "due_date": "2025-08-16",
    "priority": "Medium",
    "created_at": "2025-08-16T08:08:21.906862+00:00",
    "updated_at": "2025-08-16T08:08:21.906862+00:00",
    "completed": false,
    "pinned": false,
    "display_order": 0,
    "sort_order": 1
  },
  {
    "id": "5eae353c-3bf5-4e7d-a13e-035b909d9612",
    "user_id": "55a76048-3516-41e0-a72a-04f29ef3f518",
    "task": "a notification message: Generate a motivational morning notification for FinTask app. User has 0 pending tasks. Keep it under 50 characters, include emoji, be encouraging. Return only the message text, no quotes or extra formatting.",
    "is_completed": false,
    "due_date": "2025-08-16",
    "priority": "Medium",
    "created_at": "2025-08-16T08:14:11.014639+00:00",
    "updated_at": "2025-08-16T08:14:11.014639+00:00",
    "completed": false,
    "pinned": false,
    "display_order": 0,
    "sort_order": 1
  },
  {
    "id": "3cecec6c-821b-4562-83fa-2fe58f627763",
    "user_id": "55a76048-3516-41e0-a72a-04f29ef3f518",
    "task": "temp",
    "is_completed": false,
    "due_date": "2025-07-22",
    "priority": "Medium",
    "created_at": "2025-07-22T05:38:58.969893+00:00",
    "updated_at": "2025-08-09T09:31:50.873324+00:00",
    "completed": true,
    "pinned": false,
    "display_order": 0,
    "sort_order": 27
  },
  {
    "id": "4329fd42-d8df-4911-b3b5-03fdd22458a4",
    "user_id": "55a76048-3516-41e0-a72a-04f29ef3f518",
    "task": "temp",
    "is_completed": false,
    "due_date": "2025-07-30",
    "priority": "Medium",
    "created_at": "2025-07-22T05:38:45.387452+00:00",
    "updated_at": "2025-08-09T09:34:34.209676+00:00",
    "completed": true,
    "pinned": false,
    "display_order": 0,
    "sort_order": 26
  },
  {
    "id": "13a72490-3f7c-4fe8-995d-fbf2b7acdd56",
    "user_id": "55a76048-3516-41e0-a72a-04f29ef3f518",
    "task": "clean the garage",
    "is_completed": false,
    "due_date": "2025-08-10",
    "priority": "Medium",
    "created_at": "2025-08-09T04:52:46.43417+00:00",
    "updated_at": "2025-08-09T09:37:12.353417+00:00",
    "completed": false,
    "pinned": false,
    "display_order": 0,
    "sort_order": null
  },
  {
    "id": "7e789154-dde9-4c78-828b-6592bb43d98b",
    "user_id": "55a76048-3516-41e0-a72a-04f29ef3f518",
    "task": "cleaning task",
    "is_completed": false,
    "due_date": "2025-08-10",
    "priority": "Medium",
    "created_at": "2025-08-09T12:45:28.749923+00:00",
    "updated_at": "2025-08-09T12:49:06.047898+00:00",
    "completed": false,
    "pinned": false,
    "display_order": 0,
    "sort_order": null
  },
  {
    "id": "e34afb38-f30a-4547-a8fa-edda225b220b",
    "user_id": "55a76048-3516-41e0-a72a-04f29ef3f518",
    "task": "yemp2",
    "is_completed": false,
    "due_date": "2025-07-23",
    "priority": "Medium",
    "created_at": "2025-07-22T05:39:13.896943+00:00",
    "updated_at": "2025-08-09T12:51:06.848646+00:00",
    "completed": false,
    "pinned": true,
    "display_order": 0,
    "sort_order": 28
  },
  {
    "id": "9e598fee-9eba-45ab-8967-0af9c3f8ccdc",
    "user_id": "55a76048-3516-41e0-a72a-04f29ef3f518",
    "task": "clean the printer",
    "is_completed": false,
    "due_date": "2025-08-09",
    "priority": "Medium",
    "created_at": "2025-08-09T13:06:41.939934+00:00",
    "updated_at": "2025-08-09T13:06:41.939934+00:00",
    "completed": false,
    "pinned": false,
    "display_order": 0,
    "sort_order": null
  },
  {
    "id": "6b6244e9-ab81-44aa-aee2-cbcce42368f3",
    "user_id": "370621bf-3d54-4c3f-ae21-97a30062b0f9",
    "task": "prescription glasses",
    "is_completed": false,
    "due_date": "2025-08-10",
    "priority": "Medium",
    "created_at": "2025-07-27T17:59:17.285912+00:00",
    "updated_at": "2025-08-10T18:40:19.580269+00:00",
    "completed": false,
    "pinned": true,
    "display_order": 0,
    "sort_order": 7
  },
  {
    "id": "61db9603-6e2c-47d7-a002-4c4b153ecf51",
    "user_id": "370621bf-3d54-4c3f-ae21-97a30062b0f9",
    "task": "debt consolidation",
    "is_completed": false,
    "due_date": "2025-08-04",
    "priority": "Medium",
    "created_at": "2025-08-04T17:49:10.976363+00:00",
    "updated_at": "2025-08-12T14:42:57.861945+00:00",
    "completed": false,
    "pinned": false,
    "display_order": 0,
    "sort_order": 3
  },
  {
    "id": "38aa3610-1479-4a80-a1bb-8876dac8b812",
    "user_id": "370621bf-3d54-4c3f-ae21-97a30062b0f9",
    "task": "clean the sofa",
    "is_completed": false,
    "due_date": "2025-07-14",
    "priority": "Medium",
    "created_at": "2025-08-02T22:47:26.334166+00:00",
    "updated_at": "2025-08-12T14:42:58.151181+00:00",
    "completed": false,
    "pinned": false,
    "display_order": 0,
    "sort_order": 6
  },
  {
    "id": "ca7bfc0c-f9f7-43b2-b2b0-e67cea592c50",
    "user_id": "370621bf-3d54-4c3f-ae21-97a30062b0f9",
    "task": "check mail from dps for sreelatha",
    "is_completed": false,
    "due_date": "2025-08-01",
    "priority": "Medium",
    "created_at": "2025-08-01T18:01:46.513876+00:00",
    "updated_at": "2025-08-04T17:42:37.371292+00:00",
    "completed": true,
    "pinned": false,
    "display_order": 0,
    "sort_order": 1
  },
  {
    "id": "dc4aa58e-15b9-49eb-bf3b-b95ffe1af53a",
    "user_id": "55a76048-3516-41e0-a72a-04f29ef3f518",
    "task": "fix the sofa",
    "is_completed": false,
    "due_date": "2025-08-10",
    "priority": "Medium",
    "created_at": "2025-08-09T04:54:33.950621+00:00",
    "updated_at": "2025-08-09T09:40:31.466294+00:00",
    "completed": false,
    "pinned": true,
    "display_order": 0,
    "sort_order": null
  },
  {
    "id": "f9d78be5-ea84-40be-9da5-b94f9610639c",
    "user_id": "370621bf-3d54-4c3f-ae21-97a30062b0f9",
    "task": "check about branson trip expiry date",
    "is_completed": false,
    "due_date": "2025-07-25",
    "priority": "Medium",
    "created_at": "2025-07-25T13:31:43.854269+00:00",
    "updated_at": "2025-08-04T17:43:57.25664+00:00",
    "completed": true,
    "pinned": false,
    "display_order": 0,
    "sort_order": 8
  },
  {
    "id": "b4e64c2d-4d5a-48c7-a9da-b9c82846b15d",
    "user_id": "370621bf-3d54-4c3f-ae21-97a30062b0f9",
    "task": "amazon returns",
    "is_completed": false,
    "due_date": "2025-07-13",
    "priority": "Medium",
    "created_at": "2025-07-13T17:45:08.386143+00:00",
    "updated_at": "2025-07-22T05:01:26.374648+00:00",
    "completed": true,
    "pinned": false,
    "display_order": 29,
    "sort_order": null
  },
  {
    "id": "a8bf45e3-7372-4c67-a4f9-b26632a35ef1",
    "user_id": "370621bf-3d54-4c3f-ae21-97a30062b0f9",
    "task": "put cameras on charging",
    "is_completed": false,
    "due_date": "2025-07-31",
    "priority": "Medium",
    "created_at": "2025-07-31T14:01:27.704161+00:00",
    "updated_at": "2025-08-04T20:12:39.952593+00:00",
    "completed": true,
    "pinned": false,
    "display_order": 0,
    "sort_order": 2
  },
  {
    "id": "b2c0a431-baa8-45bd-8a35-015dca59d03f",
    "user_id": "55a76048-3516-41e0-a72a-04f29ef3f518",
    "task": "finish the bottle",
    "is_completed": false,
    "due_date": "2025-08-09",
    "priority": "Medium",
    "created_at": "2025-08-09T13:04:00.733764+00:00",
    "updated_at": "2025-08-09T13:04:00.733764+00:00",
    "completed": false,
    "pinned": false,
    "display_order": 0,
    "sort_order": null
  },
  {
    "id": "144b4666-4c01-4b75-874d-126c2526b7a4",
    "user_id": "370621bf-3d54-4c3f-ae21-97a30062b0f9",
    "task": "send june report",
    "is_completed": false,
    "due_date": "2025-07-20",
    "priority": "Medium",
    "created_at": "2025-07-17T14:59:09.304361+00:00",
    "updated_at": "2025-07-22T05:01:27.188411+00:00",
    "completed": true,
    "pinned": true,
    "display_order": 0,
    "sort_order": null
  },
  {
    "id": "e2bc6869-5dee-453b-b773-1697ef4b0738",
    "user_id": "370621bf-3d54-4c3f-ae21-97a30062b0f9",
    "task": "buy shoes and backpacks for kids",
    "is_completed": false,
    "due_date": "2025-07-31",
    "priority": "Medium",
    "created_at": "2025-07-31T15:18:40.878842+00:00",
    "updated_at": "2025-08-09T00:53:13.269703+00:00",
    "completed": true,
    "pinned": false,
    "display_order": 0,
    "sort_order": 5
  },
  {
    "id": "6d2746e5-11f7-48fd-82e6-c6b5a5eb3cc6",
    "user_id": "370621bf-3d54-4c3f-ae21-97a30062b0f9",
    "task": "diabetes check up kit",
    "is_completed": false,
    "due_date": "2025-07-20",
    "priority": "Medium",
    "created_at": "2025-07-17T14:58:43.227112+00:00",
    "updated_at": "2025-08-09T01:12:29.837323+00:00",
    "completed": true,
    "pinned": true,
    "display_order": 0,
    "sort_order": 19
  },
  {
    "id": "a6e03c63-2fb8-4174-9162-402954ddfbd2",
    "user_id": "370621bf-3d54-4c3f-ae21-97a30062b0f9",
    "task": "request H1B client letters",
    "is_completed": false,
    "due_date": "2025-07-21",
    "priority": "Medium",
    "created_at": "2025-07-17T14:58:58.243719+00:00",
    "updated_at": "2025-08-09T01:12:31.245406+00:00",
    "completed": true,
    "pinned": true,
    "display_order": 0,
    "sort_order": null
  },
  {
    "id": "e0eb8a5b-1ff3-4932-8935-d2296aa11f6b",
    "user_id": "55a76048-3516-41e0-a72a-04f29ef3f518",
    "task": "Test_E2E_Todo_9679_1755308867618",
    "is_completed": false,
    "due_date": "2025-08-15",
    "priority": "Medium",
    "created_at": "2025-08-16T01:47:52.778362+00:00",
    "updated_at": "2025-08-16T06:25:57.243144+00:00",
    "completed": true,
    "pinned": false,
    "display_order": 0,
    "sort_order": 1
  },
  {
    "id": "8aa057b9-1e64-47c4-bf2e-80c6c34f8f47",
    "user_id": "370621bf-3d54-4c3f-ae21-97a30062b0f9",
    "task": "resolve declined card issue with melissa dental",
    "is_completed": false,
    "due_date": "2025-07-28",
    "priority": "Medium",
    "created_at": "2025-07-28T13:34:41.468201+00:00",
    "updated_at": "2025-07-28T23:39:40.892194+00:00",
    "completed": true,
    "pinned": false,
    "display_order": 0,
    "sort_order": 1
  },
  {
    "id": "0242f71f-298d-48a7-8a1c-558a95edf6ee",
    "user_id": "370621bf-3d54-4c3f-ae21-97a30062b0f9",
    "task": "set up over draft with bofa",
    "is_completed": false,
    "due_date": "2025-07-28",
    "priority": "Medium",
    "created_at": "2025-07-28T23:42:25.635984+00:00",
    "updated_at": "2025-07-30T21:32:17.843198+00:00",
    "completed": true,
    "pinned": false,
    "display_order": 0,
    "sort_order": 1
  },
  {
    "id": "4d5fa51a-929d-472a-9d75-5f43156f2e00",
    "user_id": "55a76048-3516-41e0-a72a-04f29ef3f518",
    "task": "a notification message: Generate a motivational morning notification for FinTask app. User has 0 pending tasks. Keep it under 50 characters, include emoji, be encouraging. Return only the message text, no quotes or extra formatting.",
    "is_completed": false,
    "due_date": "2025-08-16",
    "priority": "Medium",
    "created_at": "2025-08-16T08:13:01.633278+00:00",
    "updated_at": "2025-08-16T08:13:01.633278+00:00",
    "completed": false,
    "pinned": false,
    "display_order": 0,
    "sort_order": 1
  },
  {
    "id": "57b144b3-9306-4994-b7ab-eda43fd6208d",
    "user_id": "55a76048-3516-41e0-a72a-04f29ef3f518",
    "task": "a notification message: Generate a motivational morning notification for FinTask app. User has 0 pending tasks. Keep it under 50 characters, include emoji, be encouraging. Return only the message text, no quotes or extra formatting.",
    "is_completed": false,
    "due_date": "2025-08-16",
    "priority": "Medium",
    "created_at": "2025-08-16T08:13:03.30468+00:00",
    "updated_at": "2025-08-16T08:13:03.30468+00:00",
    "completed": false,
    "pinned": false,
    "display_order": 0,
    "sort_order": 1
  },
  {
    "id": "e8863821-282d-4dee-a504-cf60aa21d41f",
    "user_id": "370621bf-3d54-4c3f-ae21-97a30062b0f9",
    "task": "review lca and post it",
    "is_completed": false,
    "due_date": "2025-07-28",
    "priority": "Medium",
    "created_at": "2025-07-28T13:34:11.960107+00:00",
    "updated_at": "2025-07-31T15:16:49.153849+00:00",
    "completed": true,
    "pinned": true,
    "display_order": 0,
    "sort_order": 1
  },
  {
    "id": "c3298af6-970f-4a4f-a47d-d039a21ce0e4",
    "user_id": "55a76048-3516-41e0-a72a-04f29ef3f518",
    "task": "a notification message: Generate a motivational morning notification for FinTask app. User has 0 pending tasks. Keep it under 50 characters, include emoji, be encouraging. Return only the message text, no quotes or extra formatting.",
    "is_completed": false,
    "due_date": "2025-08-16",
    "priority": "Medium",
    "created_at": "2025-08-16T08:13:06.99694+00:00",
    "updated_at": "2025-08-16T08:13:06.99694+00:00",
    "completed": false,
    "pinned": false,
    "display_order": 0,
    "sort_order": 1
  },
  {
    "id": "4c544463-ad30-4dec-960f-73bcf1e03096",
    "user_id": "55a76048-3516-41e0-a72a-04f29ef3f518",
    "task": "a notification message: Generate a motivational morning notification for FinTask app. User has 0 pending tasks. Keep it under 50 characters, include emoji, be encouraging. Return only the message text, no quotes or extra formatting.",
    "is_completed": false,
    "due_date": "2025-08-16",
    "priority": "Medium",
    "created_at": "2025-08-16T08:13:07.646665+00:00",
    "updated_at": "2025-08-16T08:13:07.646665+00:00",
    "completed": false,
    "pinned": false,
    "display_order": 0,
    "sort_order": 1
  },
  {
    "id": "7aa26659-4476-42c8-9cbc-2849c353917b",
    "user_id": "55a76048-3516-41e0-a72a-04f29ef3f518",
    "task": "a notification message: Generate a motivational morning notification for FinTask app. User has 0 pending tasks. Keep it under 50 characters, include emoji, be encouraging. Return only the message text, no quotes or extra formatting.",
    "is_completed": false,
    "due_date": "2025-08-16",
    "priority": "Medium",
    "created_at": "2025-08-16T08:14:18.87842+00:00",
    "updated_at": "2025-08-16T08:14:18.87842+00:00",
    "completed": false,
    "pinned": false,
    "display_order": 0,
    "sort_order": 1
  },
  {
    "id": "c8ebc5bd-956f-4783-88c3-1deeefd5a31b",
    "user_id": "55a76048-3516-41e0-a72a-04f29ef3f518",
    "task": "a notification message: Generate a motivational morning notification for FinTask app. User has 0 pending tasks. Keep it under 50 characters, include emoji, be encouraging. Return only the message text, no quotes or extra formatting.",
    "is_completed": false,
    "due_date": "2025-08-16",
    "priority": "Medium",
    "created_at": "2025-08-16T08:14:27.759614+00:00",
    "updated_at": "2025-08-16T08:14:27.759614+00:00",
    "completed": false,
    "pinned": false,
    "display_order": 0,
    "sort_order": 1
  },
  {
    "id": "b0b68491-d099-4a59-812c-c94d533d8212",
    "user_id": "370621bf-3d54-4c3f-ae21-97a30062b0f9",
    "task": "return money to kantham",
    "is_completed": false,
    "due_date": "2025-07-28",
    "priority": "Medium",
    "created_at": "2025-07-28T13:35:11.549006+00:00",
    "updated_at": "2025-08-02T20:39:18.633691+00:00",
    "completed": true,
    "pinned": false,
    "display_order": 0,
    "sort_order": 6
  },
  {
    "id": "51fd8d79-070d-4af3-9123-c03991c17c04",
    "user_id": "55a76048-3516-41e0-a72a-04f29ef3f518",
    "task": "Test_E2E_Todo_887_1754713340770",
    "is_completed": false,
    "due_date": "2025-08-08",
    "priority": "Medium",
    "created_at": "2025-08-09T04:22:23.596394+00:00",
    "updated_at": "2025-08-09T04:43:29.98673+00:00",
    "completed": true,
    "pinned": false,
    "display_order": 0,
    "sort_order": 34
  },
  {
    "id": "83327d34-ccee-4772-8d57-b11c4a69995a",
    "user_id": "55a76048-3516-41e0-a72a-04f29ef3f518",
    "task": "temp",
    "is_completed": false,
    "due_date": "2025-07-24",
    "priority": "Medium",
    "created_at": "2025-07-22T05:38:17.83793+00:00",
    "updated_at": "2025-08-09T09:34:34.382003+00:00",
    "completed": true,
    "pinned": false,
    "display_order": 0,
    "sort_order": 25
  },
  {
    "id": "8b5d5195-0c55-4720-ac3c-613c86efa255",
    "user_id": "370621bf-3d54-4c3f-ae21-97a30062b0f9",
    "task": "cancel mile auto policy",
    "is_completed": false,
    "due_date": "2025-08-10",
    "priority": "Medium",
    "created_at": "2025-08-03T01:12:35.589059+00:00",
    "updated_at": "2025-08-11T19:02:07.397751+00:00",
    "completed": true,
    "pinned": true,
    "display_order": 0,
    "sort_order": 4
  },
  {
    "id": "ab6152d3-376c-4964-9e18-09638c2a3e82",
    "user_id": "370621bf-3d54-4c3f-ae21-97a30062b0f9",
    "task": "fix front entrance light",
    "is_completed": false,
    "due_date": "2025-08-06",
    "priority": "Medium",
    "created_at": "2025-08-06T06:00:46.256439+00:00",
    "updated_at": "2025-08-12T14:42:57.760612+00:00",
    "completed": false,
    "pinned": false,
    "display_order": 0,
    "sort_order": 2
  },
  {
    "id": "44dfd59f-e685-4ce2-896b-f3a0e3f6614b",
    "user_id": "370621bf-3d54-4c3f-ae21-97a30062b0f9",
    "task": "plan branson trip",
    "is_completed": false,
    "due_date": "2025-08-15",
    "priority": "Medium",
    "created_at": "2025-08-04T17:44:07.66181+00:00",
    "updated_at": "2025-08-12T14:42:57.95513+00:00",
    "completed": false,
    "pinned": false,
    "display_order": 0,
    "sort_order": 4
  },
  {
    "id": "3e851736-53c1-449d-a29a-519ce75dc9aa",
    "user_id": "370621bf-3d54-4c3f-ae21-97a30062b0f9",
    "task": "clean the storage room",
    "is_completed": false,
    "due_date": "2025-07-20",
    "priority": "Medium",
    "created_at": "2025-07-20T13:31:47.797854+00:00",
    "updated_at": "2025-08-12T14:42:58.049159+00:00",
    "completed": false,
    "pinned": false,
    "display_order": 0,
    "sort_order": 5
  },
  {
    "id": "06df085f-4dfa-450c-bb33-790873fc2564",
    "user_id": "370621bf-3d54-4c3f-ae21-97a30062b0f9",
    "task": "setup autopay for bmo card",
    "is_completed": false,
    "due_date": "2025-08-13",
    "priority": "Medium",
    "created_at": "2025-08-13T18:41:13.829185+00:00",
    "updated_at": "2025-08-13T18:41:13.829185+00:00",
    "completed": false,
    "pinned": false,
    "display_order": 0,
    "sort_order": 1
  },
  {
    "id": "ac0e8dd1-16ad-462d-82d4-b40458c866dd",
    "user_id": "370621bf-3d54-4c3f-ae21-97a30062b0f9",
    "task": "allergist appointment",
    "is_completed": false,
    "due_date": "2025-08-15",
    "priority": "Medium",
    "created_at": "2025-08-15T01:57:01.764144+00:00",
    "updated_at": "2025-08-15T01:57:01.764144+00:00",
    "completed": false,
    "pinned": false,
    "display_order": 0,
    "sort_order": 1
  }
]